jwtoxide-0.2.0.dist-info/METADATA
jwtoxide-0.2.0.dist-info/RECORD
jwtoxide-0.2.0.dist-info/WHEEL
jwtoxide-0.2.0.dist-info/license_files/LICENSE
jwtoxide.libs/libgcc_s-4e37474d.so.1
jwtoxide/py.typed
jwtoxide/jwtoxide.cpython-310-aarch64-linux-gnu.so
jwtoxide/__init__.py
jwtoxide/__init__.pyi
