Metadata-Version: 2.3
Name: jwtoxide
Version: 0.2.0
Classifier: Programming Language :: Rust
Classifier: Programming Language :: Python :: Implementation :: CPython
Classifier: Programming Language :: Python :: Implementation :: PyPy
Requires-Dist: pytest ; extra == 'test'
Requires-Dist: pyjwt >=2.0.0 ; extra == 'test'
Requires-Dist: towncrier ; extra == 'changelog'
Requires-Dist: sphinx ; extra == 'docs'
Requires-Dist: autodoc ; extra == 'docs'
Requires-Dist: sphinx-rtd-theme ; extra == 'docs'
Requires-Dist: ruff ; extra == 'lint'
Requires-Dist: bump-my-version ; extra == 'version'
Provides-Extra: test
Provides-Extra: changelog
Provides-Extra: docs
Provides-Extra: lint
Provides-Extra: version
License-File: LICENSE
Requires-Python: >=3.9
